git_tag_bump.py
git_tag_bump-0.1.1.dist-info/WHEEL
git_tag_bump-0.1.1.dist-info/entry_points.txt
git_tag_bump-0.1.1.dist-info/METADATA
git_tag_bump-0.1.1.dist-info/RECORD
